pitest112/__init__.py
pitest112/example_module.py
pitest112-0.1.0.dist-info/LICENSE
pitest112-0.1.0.dist-info/METADATA
pitest112-0.1.0.dist-info/WHEEL
pitest112-0.1.0.dist-info/top_level.txt
pitest112-0.1.0.dist-info/RECORD
