Metadata-Version: 2.1
Name: pitest112
Version: 0.1.0
Summary: A simple example python package.
Home-page: https://best-practice-and-impact.github.io/example-package-python/
Author: David Foster
Author-email: david.foster@ons.gov.uk
License: MIT license
Classifier: Programming Language :: Python :: 3
Classifier: License :: OSI Approved :: MIT License
Classifier: Operating System :: OS Independent
License-File: LICENSE
